 [{
  "stadNamn":"Göteborg",
  "restaurangDetaljer": [{
 	  "restaurangNamn": "Burgers",
 	  "telefonNummer": "07634569",
 	  "hemsida": "www.burgers.com",
 	  "skapad": 2005,
 	  "adress": "Andralång gatan 5",
 	  "active": true,
 	  "personBokning": [{
 			"fornamn": "Marcus",
 			"efternamn": "Nilsson",
 			"telefonnummer": "0763413452",
 			"epost": "marcus.nilsson@hotmail.com",
 			"bokningInfo": 
               [{
 				"Bokningsnummer": 5654,
 				"Personer": "4st",
                "datum": "2019-11-22",
 				"Tid": "20:00"
               }]
 		},
 		{
 			"fornamn": "Kalle",
 			"efternamn": "Karlsson",
 			"telefonnummer": "0763465568",
 			"epost": "kalle.k@hotmail.se",
 			"bokningInfo": 
               [{
 				"Bokningsnummer": 5700,
 				"Personer": "2st",
                "datum": "2019-11-30",
 				"Tid": "19:00"
 			   }]
 		},
 		{
 			"fornamn": "Lisa",
 			"efternamn": "Andersson",
 			"telefonnummer": "0763456875",
 			"epost": "lisen33@live.se",
 			"bokningInfo": 
               [{
 				"Bokningsnummer": 5801,
 				"Personer": "8st",
                "datum": "2019-11-30",
 				"Tid": "17:00"
               }]
 		}]
      
    }]
}]

